[
  {
    "date": "25 Aug 2002",
    "time": "12:00:00",
    "content": "SetUp",
    "filename": "SetUp.mp3"
  },
  {
    "date": "19 Nov 2022",
    "time": "11:53:42",
    "content": "Cuộc chiến đã kết thúc mời các bạn abc",
    "filename": "19-Nov-2022-11-53-42.mp3"
  },
  {
    "date": "19 Nov 2022",
    "time": "18:25:29",
    "content": "Có chuyện gì vậy",
    "filename": "19-Nov-2022-18-25-28.mp3"
  },
  {
    "date": "19 Nov 2022",
    "time": "18:27:33",
    "content": "Có chuyện gì vậy",
    "filename": "19-Nov-2022-18-27-32.mp3"
  },
  {
    "date": "19 Nov 2022",
    "time": "18:27:35",
    "content": "Tôi ổn",
    "filename": "19-Nov-2022-18-27-35.mp3"
  },
  {
    "date": "19 Nov 2022",
    "time": "18:27:36",
    "content": "Cảm ơn",
    "filename": "19-Nov-2022-18-27-36.mp3"
  },
  {
    "date": "19 Nov 2022",
    "time": "18:27:38",
    "content": "Không vấn đề gì cả",
    "filename": "19-Nov-2022-18-27-38.mp3"
  },
  {
    "date": "19 Nov 2022",
    "time": "18:27:41",
    "content": "Đừng lo lắng",
    "filename": "19-Nov-2022-18-27-40.mp3"
  },
  {
    "date": "19 Nov 2022",
    "time": "18:27:42",
    "content": "Tôi phải đi đây",
    "filename": "19-Nov-2022-18-27-42.mp3"
  },
  {
    "date": "19 Nov 2022",
    "time": "18:54:09",
    "content": "Thằng Chó Đức",
    "filename": "19-Nov-2022-18-54-09.mp3"
  }
]